db_crawl_agents/__init__.py
db_crawl_agents/agents/__init__.py
db_crawl_agents/agents/evaluator.py
db_crawl_agents/agents/retry_planner.py
db_crawl_agents/agents/single_cte.py
db_crawl_agents/agents/task_decomposer.py
db_crawl_agents/agents/feature_orchestrator/__init__.py
db_crawl_agents/agents/feature_orchestrator/feature_orchestrator.py
db_crawl_agents/contracts/__init__.py
db_crawl_agents/contracts/chatmodels.py
db_crawl_agents/contracts/planner.py
db_crawl_agents/contracts/readme.md
db_crawl_agents/contracts/feature_orchestrator/__init__.py
db_crawl_agents/contracts/feature_orchestrator/feature_orchestrator.py
db_crawl_agents/contracts/feature_orchestrator/orchestrator_state.py
db_crawl_agents/contracts/reviewer/__init__.py
db_crawl_agents/contracts/single_cte/__init__.py
db_crawl_agents/contracts/single_cte/execution_results.py
db_crawl_agents/contracts/single_cte/readme.md
db_crawl_agents/contracts/single_cte/single_cte_output.py
db_crawl_agents/contracts/single_cte/single_cte_task.py
db_crawl_agents/contracts/task_decomposer/__init__.py
db_crawl_agents/contracts/task_decomposer/task_decomposer.py
db_crawl_agents/contracts/validator/__init__.py
db_crawl_agents/llms/__init__.py
db_crawl_agents/llms/readme.md
db_crawl_agents/llms/openai_integration/__init__.py
db_crawl_agents/llms/openai_integration/chat_openai.py
db_crawl_agents/llms/openai_integration/embeddings_openai.py
db_crawl_agents/nodes/feature_orchestrator/finalize_features.py
db_crawl_agents/nodes/feature_orchestrator/memory.py
db_crawl_agents/nodes/feature_orchestrator/parse_query_node.py
db_crawl_agents/nodes/feature_orchestrator/propose_features.py
db_crawl_agents/nodes/feature_orchestrator/refine_with_feedback.py
db_crawl_agents/prompts/__init__.py
db_crawl_agents/prompts/readme.md
db_crawl_agents/prompts/single_cte.py
db_crawl_agents/prompts/task_decompostion.py
db_crawl_agents/prompts/feature_extractor/__init__.py
db_crawl_agents/prompts/feature_extractor/feature_extractor.py
db_crawl_agents-0.0.8.dist-info/METADATA
db_crawl_agents-0.0.8.dist-info/WHEEL
db_crawl_agents-0.0.8.dist-info/licenses/LICENSE
db_crawl_agents-0.0.8.dist-info/RECORD
