Metadata-Version: 2.4
Name: db-crawl-agents
Version: 0.0.8
Summary: Agentic core for DB crawling.
Project-URL: Homepage, https://github.com/zuhorer/db-crawl-agent
Project-URL: Issues, https://github.com/zuhorer/db-crawl-agent/issues
Author-email: Yash Raj Singh <yashbhadauria@gmail.com>
License:                                  Apache License
License-File: LICENSE
Keywords: LLM,agents,database,executor,planner
Classifier: License :: OSI Approved :: Apache Software License
Classifier: Operating System :: OS Independent
Classifier: Programming Language :: Python :: 3
Requires-Python: >=3.9
Requires-Dist: langchain-community==0.3.29
Requires-Dist: langchain-core==0.3.76
Requires-Dist: langchain==0.3.27
Requires-Dist: langgraph==0.6.7
Requires-Dist: openai==1.107.2
Requires-Dist: pydantic<3,>=2.0
Requires-Dist: requests>=2.32.0
Requires-Dist: typing-extensions>=4.8.0; python_version < '3.11'
Provides-Extra: dev
Requires-Dist: black>=24.0; extra == 'dev'
Requires-Dist: build>=1.2.1; extra == 'dev'
Requires-Dist: mypy>=1.9; extra == 'dev'
Requires-Dist: pytest>=8.0; extra == 'dev'
Requires-Dist: twine>=5.0.0; extra == 'dev'
